yogaflo/__about__.py
yogaflo/__init__.py
yogaflo/__main__.py
yogaflo/constraints.py
yogaflo/data.py
yogaflo/yogaflo.py
yogaflo/data/poses.json
yogaflo/data/flows/flows-gavin.json
yogaflo/data/flows/flows-tobin.json
yogaflo-0.2.1.dist-info/LICENSE
yogaflo-0.2.1.dist-info/METADATA
yogaflo-0.2.1.dist-info/WHEEL
yogaflo-0.2.1.dist-info/entry_points.txt
yogaflo-0.2.1.dist-info/top_level.txt
yogaflo-0.2.1.dist-info/RECORD
