Metadata-Version: 2.1
Name: yogaflo
Version: 0.2.1
Summary: Yoga Flow Generator
Home-page: https://github.com/tyehle/yogaflo
Author: Tobin Yehle
Author-email: tobinyehle@gmail.com
License: MIT
Platform: UNKNOWN
Classifier: Development Status :: 4 - Beta
Classifier: License :: OSI Approved :: MIT License
Classifier: Programming Language :: Python :: 3
Classifier: Programming Language :: Python :: 3.6
Classifier: Programming Language :: Python :: 3.7
Classifier: Programming Language :: Python :: 3.8
Classifier: Operating System :: OS Independent
Classifier: Environment :: Console
Classifier: Typing :: Typed
Requires-Dist: markovify
